specs/Component.py
specs/ComponentManager.py
specs/Entity.py
specs/EntityManager.py
specs/Globals.py
specs/Scene.py
specs/System.py
specs/__init__.py
simple_python_ecs-0.1.1.dist-info/METADATA
simple_python_ecs-0.1.1.dist-info/WHEEL
simple_python_ecs-0.1.1.dist-info/licenses/LICENSE
simple_python_ecs-0.1.1.dist-info/RECORD
