Metadata-Version: 2.4
Name: simple-python-ecs
Version: 0.1.1
Summary: A simple to use Python ECS library.
Author-email: Rik Cross <rik.j.cross@gmail.com>
License-File: LICENSE
Classifier: License :: OSI Approved :: MIT License
Classifier: Operating System :: OS Independent
Classifier: Programming Language :: Python :: 3
Requires-Python: >=3.7
